mycli/__init__.py
mycli/cli.py
greetings_cli_umair-0.1.0.dist-info/METADATA
greetings_cli_umair-0.1.0.dist-info/WHEEL
greetings_cli_umair-0.1.0.dist-info/entry_points.txt
greetings_cli_umair-0.1.0.dist-info/top_level.txt
greetings_cli_umair-0.1.0.dist-info/RECORD
