Metadata-Version: 2.4
Name: greetings-cli-umair
Version: 0.1.0
Summary: A simple CLI app using Click(Testing).
Author: Umair Ahmed Imran
Classifier: Programming Language :: Python :: 3
Classifier: License :: OSI Approved :: MIT License
Requires-Dist: click
Dynamic: author
Dynamic: classifier
Dynamic: requires-dist
Dynamic: summary
